largekalman/__init__.py
largekalman/em.py
largekalman/filter.py
largekalman/libfilter.c
largekalman/makefile
largekalman/utils.c
largekalman-0.2.11.dist-info/licenses/LICENSE
largekalman-0.2.11.dist-info/METADATA
largekalman-0.2.11.dist-info/WHEEL
largekalman-0.2.11.dist-info/top_level.txt
largekalman-0.2.11.dist-info/RECORD
