Metadata-Version: 2.4
Name: largekalman
Version: 0.2.11
Summary: Kalman filtering and smoothing for larger-than-memory datasets
Author: Oden Petersen
License-Expression: MIT
Project-URL: Homepage, https://github.com/odenpetersen/largekalman
Project-URL: Repository, https://github.com/odenpetersen/largekalman
Keywords: kalman,filter,smoother,state-space,time-series
Classifier: Development Status :: 3 - Alpha
Classifier: Intended Audience :: Science/Research
Classifier: Operating System :: POSIX :: Linux
Classifier: Operating System :: MacOS
Classifier: Programming Language :: Python :: 3
Classifier: Programming Language :: Python :: 3.8
Classifier: Programming Language :: Python :: 3.9
Classifier: Programming Language :: Python :: 3.10
Classifier: Programming Language :: Python :: 3.11
Classifier: Programming Language :: Python :: 3.12
Classifier: Programming Language :: C
Classifier: Topic :: Scientific/Engineering
Requires-Python: >=3.8
License-File: LICENSE
Requires-Dist: numpy
Provides-Extra: dev
Requires-Dist: pytest; extra == "dev"
Requires-Dist: build; extra == "dev"
Requires-Dist: twine; extra == "dev"
Dynamic: license-file
